pdflinkcheck/__init__.py
pdflinkcheck/__main__.py
pdflinkcheck/analysis_pdfium.py
pdflinkcheck/analysis_pymupdf.py
pdflinkcheck/analysis_pypdf.py
pdflinkcheck/cli.py
pdflinkcheck/datacopy.py
pdflinkcheck/dev.py
pdflinkcheck/environment.py
pdflinkcheck/gui.py
pdflinkcheck/helpers.py
pdflinkcheck/io.py
pdflinkcheck/report copy.py
pdflinkcheck/report.py
pdflinkcheck/security.py
pdflinkcheck/splash.py
pdflinkcheck/spreadsheet.py
pdflinkcheck/stdlib_server.py
pdflinkcheck/tk_utils.py
pdflinkcheck/update_msix_version.py
pdflinkcheck/validate.py
pdflinkcheck/version_info.py
pdflinkcheck/data/I Have Questions.md
pdflinkcheck/data/LICENSE
pdflinkcheck/data/README.md
pdflinkcheck/data/pyproject.toml
pdflinkcheck/data/icons/BoxArt-1080x1080.png
pdflinkcheck/data/icons/Logo-150x150.png
pdflinkcheck/data/icons/Logo-300x300.png
pdflinkcheck/data/icons/Logo-71x71.png
pdflinkcheck/data/icons/PosterArt-720x1080.png
pdflinkcheck/data/icons/SmallLogo-44x44.png
pdflinkcheck/data/icons/SplashScreen-620x300.png
pdflinkcheck/data/icons/StoreLogo-50x50.png
pdflinkcheck/data/icons/WideLogo-310x150.png
pdflinkcheck/data/icons/red_pdf_512px.ico
pdflinkcheck/data/themes/forest/forest-dark.tcl
pdflinkcheck/data/themes/forest/forest-light.tcl
pdflinkcheck/data/themes/forest/forest-dark/border-accent-hover.png
pdflinkcheck/data/themes/forest/forest-dark/border-accent.png
pdflinkcheck/data/themes/forest/forest-dark/border-basic.png
pdflinkcheck/data/themes/forest/forest-dark/border-hover.png
pdflinkcheck/data/themes/forest/forest-dark/border-invalid.png
pdflinkcheck/data/themes/forest/forest-dark/card.png
pdflinkcheck/data/themes/forest/forest-dark/check-accent.png
pdflinkcheck/data/themes/forest/forest-dark/check-basic.png
pdflinkcheck/data/themes/forest/forest-dark/check-hover.png
pdflinkcheck/data/themes/forest/forest-dark/check-tri-accent.png
pdflinkcheck/data/themes/forest/forest-dark/check-tri-basic.png
pdflinkcheck/data/themes/forest/forest-dark/check-tri-hover.png
pdflinkcheck-1.3.5.dist-info/licenses/LICENSE
pdflinkcheck-1.3.5.dist-info/licenses/LICENSE-AGPL3
pdflinkcheck-1.3.5.dist-info/licenses/LICENSE-MIT
pdflinkcheck-1.3.5.dist-info/METADATA
pdflinkcheck-1.3.5.dist-info/WHEEL
pdflinkcheck-1.3.5.dist-info/entry_points.txt
pdflinkcheck-1.3.5.dist-info/top_level.txt
pdflinkcheck-1.3.5.dist-info/RECORD
