Metadata-Version: 2.4
Name: pdflinkcheck
Version: 1.3.5
Summary: A purpose-built PDF link analysis and reporting tool with GUI and CLI.
Author-email: George Clayton Bennett <george.bennett@memphistn.gov>
Maintainer-email: George Clayton Bennett <george.bennett@memphistn.gov>
License-Expression: MIT AND AGPL-3.0-or-later
Project-URL: Homepage, https://github.com/city-of-memphis-wastewater/pdflinkcheck
Project-URL: Repository, https://github.com/city-of-memphis-wastewater/pdflinkcheck
Classifier: Programming Language :: Python :: 3
Classifier: Programming Language :: Python :: 3 :: Only
Classifier: Programming Language :: Python :: 3.9
Classifier: Programming Language :: Python :: 3.10
Classifier: Programming Language :: Python :: 3.11
Classifier: Programming Language :: Python :: 3.12
Classifier: Programming Language :: Python :: 3.13
Classifier: Programming Language :: Python :: 3.14
Classifier: Operating System :: OS Independent
Classifier: Intended Audience :: End Users/Desktop
Classifier: Intended Audience :: Developers
Classifier: Intended Audience :: Science/Research
Classifier: Intended Audience :: Other Audience
Classifier: Topic :: File Formats
Classifier: Topic :: Office/Business
Classifier: Topic :: Text Processing :: General
Classifier: Topic :: Scientific/Engineering :: Information Analysis
Classifier: Environment :: Console
Classifier: Environment :: MacOS X
Classifier: Environment :: Win32 (MS Windows)
Classifier: Typing :: Typed
Classifier: Development Status :: 4 - Beta
Requires-Python: >=3.9
License-File: LICENSE
License-File: LICENSE-MIT
License-File: LICENSE-AGPL3
Requires-Dist: openpyxl>=3.1.5
Requires-Dist: pyhabitat>=1.1.6
Requires-Dist: pypdf>=6.4.2
Requires-Dist: rich>=14.2.0
Requires-Dist: typer>=0.20.0
Provides-Extra: pymupdf
Requires-Dist: pymupdf<2.0.0,>=1.24.0; extra == "pymupdf"
Provides-Extra: pdfium
Requires-Dist: pypdfium2<6.0.0,>=5.2.0; extra == "pdfium"
Provides-Extra: full
Requires-Dist: pymupdf<2.0.0,>=1.24.0; extra == "full"
Requires-Dist: pypdfium2<6.0.0,>=5.2.0; extra == "full"
Dynamic: license-file
